django_deadcode/__init__.py
django_deadcode/apps.py
django_deadcode/analyzers/__init__.py
django_deadcode/analyzers/reverse_analyzer.py
django_deadcode/analyzers/template_analyzer.py
django_deadcode/analyzers/url_analyzer.py
django_deadcode/analyzers/view_analyzer.py
django_deadcode/management/__init__.py
django_deadcode/management/commands/__init__.py
django_deadcode/management/commands/finddeadcode.py
django_deadcode/reporters/__init__.py
django_deadcode/reporters/base.py
django_deadcode/utils/__init__.py
django_deadcode/utils/config.py
django_deadcode/utils/module_detection.py
django_deadcode/utils/url_matching.py
django_deadcode-0.8.0.dist-info/licenses/LICENSE
django_deadcode-0.8.0.dist-info/METADATA
django_deadcode-0.8.0.dist-info/WHEEL
django_deadcode-0.8.0.dist-info/top_level.txt
django_deadcode-0.8.0.dist-info/RECORD
