Metadata-Version: 2.4
Name: django-deadcode
Version: 0.8.0
Summary: A Django dead code analysis tool that tracks relationships between templates, URLs, and views
Author-email: Your Name <your.email@example.com>
License: MIT
Project-URL: Homepage, https://github.com/nanorepublica/django-deadcode
Project-URL: Repository, https://github.com/nanorepublica/django-deadcode
Project-URL: Issues, https://github.com/nanorepublica/django-deadcode/issues
Keywords: django,dead-code,static-analysis,code-quality
Classifier: Development Status :: 3 - Alpha
Classifier: Framework :: Django
Classifier: Framework :: Django :: 4.2
Classifier: Framework :: Django :: 5.0
Classifier: Framework :: Django :: 5.1
Classifier: Intended Audience :: Developers
Classifier: License :: OSI Approved :: MIT License
Classifier: Operating System :: OS Independent
Classifier: Programming Language :: Python :: 3
Classifier: Programming Language :: Python :: 3.10
Classifier: Programming Language :: Python :: 3.11
Classifier: Programming Language :: Python :: 3.12
Classifier: Programming Language :: Python :: 3.13
Classifier: Topic :: Software Development :: Quality Assurance
Requires-Python: >=3.10
License-File: LICENSE
Requires-Dist: Django>=4.2
Provides-Extra: dev
Requires-Dist: pytest>=7.0; extra == "dev"
Requires-Dist: pytest-django>=4.5; extra == "dev"
Requires-Dist: pytest-cov>=4.0; extra == "dev"
Requires-Dist: ruff>=0.1.0; extra == "dev"
Requires-Dist: mypy>=1.0; extra == "dev"
Requires-Dist: django-stubs>=4.2; extra == "dev"
Dynamic: license-file
